{
    "wallpaper": "/home/sluchess/.config/wpg/wallpapers/LandscapeArchPano.jpg",
    "alpha": "100",

    "special": {
        "background": "#151309",
        "foreground": "#e0e6ec",
        "cursor": "#e0e6ec"
    },
    "colors": {
        "color0": "#151309",
        "color1": "#AB8C62",
        "color2": "#D09E71",
        "color3": "#6A8DA8",
        "color4": "#68A2E0",
        "color5": "#E2B38A",
        "color6": "#BEC1C8",
        "color7": "#e0e6ec",
        "color8": "#9ca1a5",
        "color9": "#AB8C62",
        "color10": "#D09E71",
        "color11": "#6A8DA8",
        "color12": "#68A2E0",
        "color13": "#E2B38A",
        "color14": "#BEC1C8",
        "color15": "#e0e6ec"
    }
}
