{
    "wallpaper": "/home/sluchess/.config/wpg/wallpapers/170_-_ukkBpOO.jpg",
    "alpha": "100",

    "special": {
        "background": "#0a0602",
        "foreground": "#e1d69c",
        "cursor": "#e1d69c"
    },
    "colors": {
        "color0": "#0a0602",
        "color1": "#8F511D",
        "color2": "#A05C21",
        "color3": "#B66D26",
        "color4": "#C17B2B",
        "color5": "#C58C30",
        "color6": "#D0B23C",
        "color7": "#e1d69c",
        "color8": "#9d956d",
        "color9": "#8F511D",
        "color10": "#A05C21",
        "color11": "#B66D26",
        "color12": "#C17B2B",
        "color13": "#C58C30",
        "color14": "#D0B23C",
        "color15": "#e1d69c"
    }
}
